gffutilsAI/__init__.py
gffutilsAI/gff_tools.py
gffutilsAI/main.py
gffutilsAI/system_prompt.txt
gffutilsai-0.1.17.dist-info/licenses/LICENSE
gffutilsai-0.1.17.dist-info/METADATA
gffutilsai-0.1.17.dist-info/WHEEL
gffutilsai-0.1.17.dist-info/entry_points.txt
gffutilsai-0.1.17.dist-info/top_level.txt
gffutilsai-0.1.17.dist-info/RECORD
