Metadata-Version: 2.4
Name: gffutilsai
Version: 0.1.17
Summary: Using gffutil Python module with AI
License-Expression: GPL-3.0
Requires-Python: >=3.12
License-File: LICENSE
Requires-Dist: gffutils>=0.13
Requires-Dist: strands-agents[anthropic,gemini,ollama,openai]>=1.10.0
Requires-Dist: strands-agents-tools>=0.2.9
Requires-Dist: biopython>=1.85
Requires-Dist: python-dotenv>=1.0.0
Dynamic: license-file
